{
    "level": {
        "objects": {
            "KeyObj": {
                "x": "1880",
                "y": "23"
            },
            "ExitDoor": {
                "x": "29",
                "y": "276"
            },
            "StoneMoveD": [
                {
                    "x": "288",
                    "y": "208"
                },
                {
                    "x": "1003",
                    "y": "106"
                }
            ],
            "BallItem": {
                "x": "22",
                "y": "19"
            },
            "ClimbItem": {
                "x": "1879",
                "y": "264"
            },
            "StoneMove": [
                {
                    "x": "1581",
                    "y": "304"
                },
                {
                    "x": "620",
                    "y": "109"
                }
            ],
            "StoneHiddenShow": [
                {
                    "x": "1785",
                    "y": "305"
                },
                {
                    "x": "815",
                    "y": "226"
                },
                {
                    "x": "815",
                    "y": "245"
                },
                {
                    "x": "815",
                    "y": "265"
                },
                {
                    "x": "815",
                    "y": "286"
                },
                {
                    "x": "729",
                    "y": "109"
                },
                {
                    "x": "1109",
                    "y": "293"
                }
            ],
            "StabR": [
                {
                    "x": "224",
                    "y": "177"
                },
                {
                    "x": "224",
                    "y": "163"
                },
                {
                    "x": "224",
                    "y": "149"
                }
            ],
            "Enemy": [
                {
                    "x": "1470",
                    "y": "274"
                },
                {
                    "x": "633",
                    "y": "278"
                },
                {
                    "x": "1288",
                    "y": "114"
                }
            ],
            "Stab": [
                {
                    "x": "472",
                    "y": "296"
                },
                {
                    "x": "486",
                    "y": "296"
                },
                {
                    "x": "540",
                    "y": "296"
                },
                {
                    "x": "526",
                    "y": "296"
                },
                {
                    "x": "600",
                    "y": "296"
                },
                {
                    "x": "586",
                    "y": "296"
                },
                {
                    "x": "678",
                    "y": "296"
                },
                {
                    "x": "664",
                    "y": "296"
                },
                {
                    "x": "589",
                    "y": "136"
                },
                {
                    "x": "575",
                    "y": "136"
                },
                {
                    "x": "619",
                    "y": "136"
                },
                {
                    "x": "605",
                    "y": "136"
                },
                {
                    "x": "648",
                    "y": "136"
                },
                {
                    "x": "634",
                    "y": "136"
                },
                {
                    "x": "678",
                    "y": "136"
                },
                {
                    "x": "664",
                    "y": "136"
                },
                {
                    "x": "706",
                    "y": "136"
                },
                {
                    "x": "692",
                    "y": "136"
                },
                {
                    "x": "734",
                    "y": "136"
                },
                {
                    "x": "720",
                    "y": "136"
                },
                {
                    "x": "760",
                    "y": "136"
                },
                {
                    "x": "746",
                    "y": "136"
                },
                {
                    "x": "787",
                    "y": "136"
                },
                {
                    "x": "773",
                    "y": "136"
                },
                {
                    "x": "999",
                    "y": "136"
                },
                {
                    "x": "1013",
                    "y": "136"
                },
                {
                    "x": "972",
                    "y": "136"
                },
                {
                    "x": "986",
                    "y": "136"
                },
                {
                    "x": "946",
                    "y": "136"
                },
                {
                    "x": "960",
                    "y": "136"
                },
                {
                    "x": "918",
                    "y": "136"
                },
                {
                    "x": "932",
                    "y": "136"
                },
                {
                    "x": "890",
                    "y": "136"
                },
                {
                    "x": "904",
                    "y": "136"
                },
                {
                    "x": "860",
                    "y": "136"
                },
                {
                    "x": "874",
                    "y": "136"
                },
                {
                    "x": "831",
                    "y": "136"
                },
                {
                    "x": "845",
                    "y": "136"
                },
                {
                    "x": "801",
                    "y": "136"
                },
                {
                    "x": "815",
                    "y": "136"
                }
            ],
            "Stone": [
                {
                    "x": "1096",
                    "y": "221"
                },
                {
                    "x": "877",
                    "y": "109"
                },
                {
                    "x": "1468",
                    "y": "258"
                },
                {
                    "x": "1708",
                    "y": "304"
                }
            ],
            "StabD": {
                "x": "1103",
                "y": "236"
            },
            "Hero": {
                "x": "85",
                "y": "251"
            },
            "StabHidden": [
                {
                    "x": "1472",
                    "y": "250"
                },
                {
                    "x": "1712",
                    "y": "296"
                }
            ],
            "Coin": {
                "x": "1705",
                "y": "17"
            }
        }
    }
}